codectl/__init__.py
codectl/compiler.py
codectl/jinja.py
codectl/manage.py
codectl/schema.py
codectl/settings.py
codectl/utils.py
codectl-0.1.6.dist-info/LICENSE
codectl-0.1.6.dist-info/METADATA
codectl-0.1.6.dist-info/WHEEL
codectl-0.1.6.dist-info/entry_points.txt
codectl-0.1.6.dist-info/RECORD
