Metadata-Version: 2.1
Name: codectl
Version: 0.1.6
Summary: 
Author: whc
Author-email: 249768447@qq.com
Requires-Python: >=3.10,<4.0
Classifier: Programming Language :: Python :: 3
Classifier: Programming Language :: Python :: 3.10
Classifier: Programming Language :: Python :: 3.11
Classifier: Programming Language :: Python :: 3.12
Requires-Dist: case-convert (>=1.1.0,<2.0.0)
Requires-Dist: click (>=8.1.7,<9.0.0)
Requires-Dist: deepmerge (>=1.1.1,<2.0.0)
Requires-Dist: jinja2 (>=3.1.3,<4.0.0)
Requires-Dist: jsonschema (>=4.21.1,<5.0.0)
Requires-Dist: python-dotenv (>=1.0.1,<2.0.0)
Requires-Dist: referencing (>=0.34.0,<0.35.0)
